arisu/__init__.py
arisu/__main__.py
arisu/build.py
arisu/config.py
arisu/devserver.py
arisu/extensions/__init__.py
arisu/extensions/template.py
arisu/loaders/__init__.py
arisu/loaders/content.py
arisu/renderer.py
arisu/utils.py
arisu-0.1.2.dist-info/WHEEL
arisu-0.1.2.dist-info/entry_points.txt
arisu-0.1.2.dist-info/METADATA
arisu-0.1.2.dist-info/RECORD
