Metadata-Version: 2.1
Name: arisu
Version: 0.1.2
Summary: 
License: MIT
Author: Alex Zhang
Author-email: zhangchi0104@live.com
Requires-Python: >=3.8,<4.0
Classifier: License :: OSI Approved :: MIT License
Classifier: Programming Language :: Python :: 3
Classifier: Programming Language :: Python :: 3.8
Classifier: Programming Language :: Python :: 3.9
Classifier: Programming Language :: Python :: 3.10
Classifier: Programming Language :: Python :: 3.11
Requires-Dist: Flask (>=2.2.3,<3.0.0)
Requires-Dist: jinja2 (>=3.1.2,<4.0.0)
Requires-Dist: mistune (>=2.0.5,<3.0.0)
Requires-Dist: multiprocess (>=0.70.14,<0.71.0)
Requires-Dist: pydantic (>=1.10.7,<2.0.0)
Requires-Dist: python-benedict (>=0.30.0,<0.31.0)
Requires-Dist: rich (>=13.3.3,<14.0.0)
Requires-Dist: tomli (>=2.0.1,<3.0.0)
Requires-Dist: watchdog (>=3.0.0,<4.0.0)
Requires-Dist: websockets (>=11.0,<12.0)
